lwlPackage/__init__.py
lwlPackage/__version__.py
lwlPackage/core.py
lwlPackage/test.py
lwlPackage/PathPro/__init__.py
lwlPackage/PathPro/path.py
lwlPackage/变量存储与加载/__init__.py
lwlPackage/变量存储与加载/varLD.py
lwlPackage/变量存储与加载/varLDnp.py
lwlPackage/将md得图片转存到github/__init__.py
lwlPackage/将md得图片转存到github/down_img.py
lwlPackage/将md得图片转存到github/readMD.py
lwlPackage/邮件发送/__init__.py
lwlPackage/邮件发送/message.py
lwlPackge/__init__.py
lwlPackge/__version__.py
lwlPackge/core.py
lwlpackage-0.1.4.dist-info/LICENSE
lwlpackage-0.1.4.dist-info/METADATA
lwlpackage-0.1.4.dist-info/WHEEL
lwlpackage-0.1.4.dist-info/top_level.txt
lwlpackage-0.1.4.dist-info/RECORD
